README.md
setup.py
raygun_tap_mysql.egg-info/PKG-INFO
raygun_tap_mysql.egg-info/SOURCES.txt
raygun_tap_mysql.egg-info/dependency_links.txt
raygun_tap_mysql.egg-info/entry_points.txt
raygun_tap_mysql.egg-info/requires.txt
raygun_tap_mysql.egg-info/top_level.txt
tap_mysql/__init__.py
tap_mysql/connection.py
tap_mysql/discover_utils.py
tap_mysql/stream_utils.py
tap_mysql/sync_strategies/binlog.py
tap_mysql/sync_strategies/common.py
tap_mysql/sync_strategies/full_table.py
tap_mysql/sync_strategies/incremental.py