Metadata-Version: 2.1
Name: raygun-tap-mysql
Version: 1.3.10
Summary: Singer.io tap for extracting data from MySQL - PipelineWise compatible
Home-page: https://github.com/lfalvey/pipelinewise-tap-mysql
Author: TransferWise
License: UNKNOWN
Platform: UNKNOWN
Classifier: License :: OSI Approved :: GNU Affero General Public License v3
Classifier: Programming Language :: Python :: 3 :: Only
Provides-Extra: test
